odoo/addons/survey_crm_generation/README.rst
odoo/addons/survey_crm_generation/__init__.py
odoo/addons/survey_crm_generation/__manifest__.py
odoo/addons/survey_crm_generation/demo/survey_crm_demo.xml
odoo/addons/survey_crm_generation/i18n/es.po
odoo/addons/survey_crm_generation/i18n/it.po
odoo/addons/survey_crm_generation/i18n/survey_crm_generation.pot
odoo/addons/survey_crm_generation/models/__init__.py
odoo/addons/survey_crm_generation/models/crm_lead.py
odoo/addons/survey_crm_generation/models/survey_question.py
odoo/addons/survey_crm_generation/models/survey_survey.py
odoo/addons/survey_crm_generation/models/survey_user_input.py
odoo/addons/survey_crm_generation/readme/CONFIGURE.rst
odoo/addons/survey_crm_generation/readme/CONTRIBUTORS.rst
odoo/addons/survey_crm_generation/readme/DESCRIPTION.rst
odoo/addons/survey_crm_generation/readme/USAGE.rst
odoo/addons/survey_crm_generation/static/description/icon.png
odoo/addons/survey_crm_generation/static/description/index.html
odoo/addons/survey_crm_generation/static/tests/survey_crm_generation_tour.js
odoo/addons/survey_crm_generation/tests/__init__.py
odoo/addons/survey_crm_generation/tests/test_survey_crm_sale_generation.py
odoo/addons/survey_crm_generation/views/assets.xml
odoo/addons/survey_crm_generation/views/crm_lead_views.xml
odoo/addons/survey_crm_generation/views/survey_question_views.xml
odoo/addons/survey_crm_generation/views/survey_survey_views.xml
odoo/addons/survey_crm_generation/views/survey_user_input_views.xml
odoo13_addon_survey_crm_generation-13.0.1.0.1.dev8.dist-info/METADATA
odoo13_addon_survey_crm_generation-13.0.1.0.1.dev8.dist-info/WHEEL
odoo13_addon_survey_crm_generation-13.0.1.0.1.dev8.dist-info/top_level.txt
odoo13_addon_survey_crm_generation-13.0.1.0.1.dev8.dist-info/RECORD
